README
setup.py
RESTfulEf.egg-info/PKG-INFO
RESTfulEf.egg-info/SOURCES.txt
RESTfulEf.egg-info/dependency_links.txt
RESTfulEf.egg-info/top_level.txt
restful/__init__.py
restful/api.py
restful/model.py