Metadata-Version: 1.0
Name: RESTfulEf
Version: 0.1.1
Summary: A generic restful api generator based on elixir and flask
Home-page: http://projects.comum.org/restful
Author: Lincoln de Sousa
Author-email: lincoln@comum.org
License: AGPLv3+
Keywords: rest api flask elixir
Platform: UNKNOWN
Classifier: Development Status :: 4 - Beta
Classifier: Environment :: Web Environment
Classifier: Intended Audience :: Developers
Classifier: License :: OSI Approved :: GNU Affero General Public License v3
Classifier: Operating System :: POSIX
Classifier: Programming Language :: Python
Classifier: Topic :: Database
Classifier: Topic :: Database :: Front-Ends
Classifier: Topic :: Internet :: WWW/HTTP
